<annotation>
	<folder>pitaya</folder>
	<filename>pitaya (24).jpg</filename>
	<path>D:\images\fruit_detection\JPEGImages\pitaya\pitaya (24).jpg</path>
	<source>
		<database>Unknown</database>
	</source>
	<size>
		<width>800</width>
		<height>800</height>
		<depth>3</depth>
	</size>
	<segmented>0</segmented>
	<object>
		<name>pitaya</name>
		<pose>Unspecified</pose>
		<truncated>0</truncated>
		<difficult>0</difficult>
		<bndbox>
			<xmin>73</xmin>
			<ymin>126</ymin>
			<xmax>470</xmax>
			<ymax>436</ymax>
		</bndbox>
	</object>
	<object>
		<name>pitaya</name>
		<pose>Unspecified</pose>
		<truncated>0</truncated>
		<difficult>0</difficult>
		<bndbox>
			<xmin>157</xmin>
			<ymin>394</ymin>
			<xmax>561</xmax>
			<ymax>738</ymax>
		</bndbox>
	</object>
	<object>
		<name>pitaya</name>
		<pose>Unspecified</pose>
		<truncated>1</truncated>
		<difficult>0</difficult>
		<bndbox>
			<xmin>369</xmin>
			<ymin>135</ymin>
			<xmax>800</xmax>
			<ymax>621</ymax>
		</bndbox>
	</object>
</annotation>
