<annotation>
	<folder>strawberry</folder>
	<filename>strawberry (9).jpg</filename>
	<path>D:\images\fruit_detection\JPEGImages\strawberry\strawberry (9).jpg</path>
	<source>
		<database>Unknown</database>
	</source>
	<size>
		<width>2094</width>
		<height>2950</height>
		<depth>3</depth>
	</size>
	<segmented>0</segmented>
	<object>
		<name>strawberry</name>
		<pose>Unspecified</pose>
		<truncated>0</truncated>
		<difficult>0</difficult>
		<bndbox>
			<xmin>538</xmin>
			<ymin>1457</ymin>
			<xmax>1603</xmax>
			<ymax>2593</ymax>
		</bndbox>
	</object>
	<object>
		<name>strawberry</name>
		<pose>Unspecified</pose>
		<truncated>1</truncated>
		<difficult>0</difficult>
		<bndbox>
			<xmin>1086</xmin>
			<ymin>428</ymin>
			<xmax>2094</xmax>
			<ymax>1493</ymax>
		</bndbox>
	</object>
</annotation>
